LICENSE
wica/__init__.py
wica/examples.py
wica/exceptions.py
wica/sseclient.py
wica/stream.py
wica/utils.py
wica-1.0.6.dist-info/LICENSE
wica-1.0.6.dist-info/WHEEL
wica-1.0.6.dist-info/METADATA
wica-1.0.6.dist-info/RECORD
