Metadata-Version: 2.1
Name: wica
Version: 1.0.6
Summary: A simple python API to access wica-http SSE.
Home-page: https://git.psi.ch/proscan_data/py-wica
License: GPL v3
Keywords: wica-http,wica,async,SSE,PSI
Author: Niklas Laufkoetter
Author-email: niklas.laufkoetter@psi.ch
Requires-Python: >=3.8,<4.0
Classifier: License :: Other/Proprietary License
Classifier: Operating System :: OS Independent
Classifier: Programming Language :: Python :: 3
Classifier: Programming Language :: Python :: 3.8
Classifier: Programming Language :: Python :: 3.9
Classifier: Programming Language :: Python :: 3.10
Classifier: Programming Language :: Python :: 3.11
Classifier: Programming Language :: Python :: 3
Requires-Dist: requests (>=2.28.1,<3.0.0)
Project-URL: Repository, https://git.psi.ch/proscan_data/py-wica
